acs_chatbot/__init__.py
acs_chatbot/core.py
tests/__init__.py
tests/test_core.py
acs_chatbot-0.1.1.dist-info/METADATA
acs_chatbot-0.1.1.dist-info/WHEEL
acs_chatbot-0.1.1.dist-info/top_level.txt
acs_chatbot-0.1.1.dist-info/RECORD
